das/__init__.py
das/app.py
das/cli.py
das/ai/plugins/dasai.py
das/ai/plugins/entries/entries_plugin.py
das/authentication/auth.py
das/authentication/secure_input.py
das/common/api.py
das/common/config.py
das/common/entry_fields_constants.py
das/common/enums.py
das/common/file_utils.py
das/managers/__init__.py
das/managers/digital_objects_manager.py
das/managers/download_manager.py
das/managers/entries_manager.py
das/managers/search_manager.py
das/services/attributes.py
das/services/cache.py
das/services/digital_objects.py
das/services/downloads.py
das/services/entries.py
das/services/entry_fields.py
das/services/hangfire.py
das/services/search.py
das/services/users.py
das_cli-1.2.0.dist-info/licenses/LICENSE
das_cli-1.2.0.dist-info/METADATA
das_cli-1.2.0.dist-info/WHEEL
das_cli-1.2.0.dist-info/entry_points.txt
das_cli-1.2.0.dist-info/top_level.txt
das_cli-1.2.0.dist-info/RECORD
