Metadata-Version: 2.4
Name: das-cli
Version: 1.2.0
Summary: DAS api client.
Author: Royal Netherlands Institute for Sea Research
License-Expression: MIT
Project-URL: Homepage, https://git.nioz.nl/ict-projects/das-cli
Project-URL: Bug Tracker, https://git.nioz.nl/ict-projects/das-cli/-/issues
Classifier: Programming Language :: Python :: 3
Classifier: Operating System :: OS Independent
Requires-Python: >=3.9
License-File: LICENSE
Requires-Dist: click>=8.2.1
Requires-Dist: requests>=2.32.3
Requires-Dist: python-dotenv>=1.0.0
Provides-Extra: excel
Requires-Dist: pandas>=2.2.3; extra == "excel"
Requires-Dist: openpyxl>=3.1.5; extra == "excel"
Provides-Extra: ai
Requires-Dist: semantic-kernel>=1.37.0; extra == "ai"
Dynamic: license-file
